aixm/__init__.py
aixm/_internal/__init__.py
aixm/_internal/path.py
aixm/cmd/__init__.py
aixm/cmd/compile.cpython-36m-aarch64-linux-gnu.so
aixm/cmd/file_and_dir_op.cpython-36m-aarch64-linux-gnu.so
aixm/cmd/lab2dk.cpython-36m-aarch64-linux-gnu.so
aixm/cmd/make_filter.cpython-36m-aarch64-linux-gnu.so
aixm/cmd/darknet_cfg/__init__.py
aixm/cmd/darknet_cfg/package_path.py
aixm/cmd/darknet_cfg/yolov3-15m-288.cfg
aixm/cmd/darknet_cfg/yolov3-235m-608.cfg
aixm/cmd/darknet_cfg/yolov3-35m-416.cfg
aixm/contrib/__init__.py
aixm/contrib/flask/__init__.py
aixm/contrib/flask/create_app.py
aixm/contrib/flask/parse_request.py
aixm/contrib/tfkeras/__init__.py
aixm/contrib/tfkeras/dataset.cpython-36m-aarch64-linux-gnu.so
aixm/contrib/tfkeras/session.py
aixm/contrib/vpf/__init__.py
aixm/contrib/vpf/nv_codec.py
aixm/cv/__init__.py
aixm/cv/box.cpython-36m-aarch64-linux-gnu.so
aixm/cv/direction.cpython-36m-aarch64-linux-gnu.so
aixm/cv/image.cpython-36m-aarch64-linux-gnu.so
aixm/cv/region_polygonal.cpython-36m-aarch64-linux-gnu.so
aixm/cv/straight_line.cpython-36m-aarch64-linux-gnu.so
aixm/cv/video_capture.cpython-36m-aarch64-linux-gnu.so
aixm/cv/video_capture_background.cpython-36m-aarch64-linux-gnu.so
aixm/cv/cap_impl/__init__.py
aixm/cv/cap_impl/cap_template.py
aixm/cv/cap_impl/default_cap.py
aixm/cv/cap_impl/nvi_cap.py
aixm/utils/__init__.py
aixm/utils/convert.cpython-36m-aarch64-linux-gnu.so
aixm/utils/dsop.cpython-36m-aarch64-linux-gnu.so
aixm/utils/lock.cpython-36m-aarch64-linux-gnu.so
aixm/utils/logging.cpython-36m-aarch64-linux-gnu.so
aixm/utils/logging_server.cpython-36m-aarch64-linux-gnu.so
aixm/utils/path.cpython-36m-aarch64-linux-gnu.so
aixm/utils/strategy.cpython-36m-aarch64-linux-gnu.so
aixm/utils/utils.cpython-36m-aarch64-linux-gnu.so
aixm/utils/working.cpython-36m-aarch64-linux-gnu.so
aixm/utils/ztimer.cpython-36m-aarch64-linux-gnu.so
aixm/zrpc/__init__.py
aixm/zrpc/client.cpython-36m-aarch64-linux-gnu.so
aixm/zrpc/context.cpython-36m-aarch64-linux-gnu.so
aixm_arm-0.3.2.8.dist-info/METADATA
aixm_arm-0.3.2.8.dist-info/WHEEL
aixm_arm-0.3.2.8.dist-info/entry_points.txt
aixm_arm-0.3.2.8.dist-info/top_level.txt
aixm_arm-0.3.2.8.dist-info/RECORD
