Metadata-Version: 2.1
Name: aixm-arm
Version: 0.3.2.8
Summary: aixm
Home-page: https://github.com/zxh1993
Author: zhangxinhao
Author-email: 471207747@qq.com
License: BSD License
Platform: all
Classifier: Operating System :: OS Independent
Classifier: Intended Audience :: Developers
Classifier: License :: OSI Approved :: BSD License
Classifier: Programming Language :: Python :: 3.6
Requires-Dist: Werkzeug
Requires-Dist: redis (>=3.1.0)
